dagster_polars/__init__.py
dagster_polars/constants.py
dagster_polars/patito.py
dagster_polars/py.typed
dagster_polars/types.py
dagster_polars/version.py
dagster_polars/io_managers/__init__.py
dagster_polars/io_managers/base.py
dagster_polars/io_managers/bigquery.py
dagster_polars/io_managers/delta.py
dagster_polars/io_managers/parquet.py
dagster_polars/io_managers/type_routers.py
dagster_polars/io_managers/utils.py
dagster_polars-0.27.8.dist-info/METADATA
dagster_polars-0.27.8.dist-info/WHEEL
dagster_polars-0.27.8.dist-info/top_level.txt
dagster_polars-0.27.8.dist-info/RECORD
